blob_storage_connector_wodecjak/__init__.py
blob_storage_connector_wodecjak/blob_storage_connector.py
blob_storage_connector_wodecjak-0.0.4.dist-info/LICENSE
blob_storage_connector_wodecjak-0.0.4.dist-info/METADATA
blob_storage_connector_wodecjak-0.0.4.dist-info/WHEEL
blob_storage_connector_wodecjak-0.0.4.dist-info/top_level.txt
blob_storage_connector_wodecjak-0.0.4.dist-info/RECORD
