Metadata-Version: 2.1
Name: blob_storage_connector_wodecjak
Version: 0.0.4
Summary: A package to be SOLID
Author-email: Jakub Wodecki <jakubwodecki@outlook.cz>
Classifier: Programming Language :: Python :: 3
Classifier: License :: OSI Approved :: MIT License
Classifier: Operating System :: OS Independent
Requires-Python: >=3.9
License-File: LICENSE
